energyplus_rpd/ASHRAE229.schema.json
energyplus_rpd/ASHRAE229_extra.schema.yaml
energyplus_rpd/Enumerations2019ASHRAE901.schema.json
energyplus_rpd/Enumerations2019T24.schema.json
energyplus_rpd/EnumerationsRESNET.schema.json
energyplus_rpd/Output2019ASHRAE901.schema.json
energyplus_rpd/RCT_project_output_test_report.schema.json
energyplus_rpd/RCT_software_output_test_report.schema.json
energyplus_rpd/__init__.py
energyplus_rpd/__main__.py
energyplus_rpd/compliance_parameter_handler.py
energyplus_rpd/input_file.py
energyplus_rpd/output_file.py
energyplus_rpd/runner.py
energyplus_rpd/status_reporter.py
energyplus_rpd/translator.py
energyplus_rpd/validator.py
energyplus_rpd/example/ASHRAE901_OfficeSmall_STD2019_Denver.audit
energyplus_rpd/example/ASHRAE901_OfficeSmall_STD2019_Denver.bnd
energyplus_rpd/example/ASHRAE901_OfficeSmall_STD2019_Denver.csv
energyplus_rpd/example/ASHRAE901_OfficeSmall_STD2019_Denver.eio
energyplus_rpd/example/ASHRAE901_OfficeSmall_STD2019_Denver.epJSON
energyplus_rpd/example/ASHRAE901_OfficeSmall_STD2019_Denver.err
energyplus_rpd/example/ASHRAE901_OfficeSmall_STD2019_Denver.eso
energyplus_rpd/example/ASHRAE901_OfficeSmall_STD2019_Denver.idf
energyplus_rpd/example/ASHRAE901_OfficeSmall_STD2019_Denver.json
energyplus_rpd/example/ASHRAE901_OfficeSmall_STD2019_Denver.mdd
energyplus_rpd/example/ASHRAE901_OfficeSmall_STD2019_Denver.mtd
energyplus_rpd/example/ASHRAE901_OfficeSmall_STD2019_Denver.mtr
energyplus_rpd/example/ASHRAE901_OfficeSmall_STD2019_Denver.rdd
energyplus_rpd/example/ASHRAE901_OfficeSmall_STD2019_Denver.rpd
energyplus_rpd/example/ASHRAE901_OfficeSmall_STD2019_Denver.rvaudit
energyplus_rpd/example/ASHRAE901_OfficeSmall_STD2019_Denver.shd
energyplus_rpd/example/ASHRAE901_OfficeSmall_STD2019_Denver.svg
energyplus_rpd/example/ASHRAE901_OfficeSmall_STD2019_DenverMeter.csv
energyplus_rpd/example/ASHRAE901_OfficeSmall_STD2019_DenverTable.html
energyplus_rpd/example/ASHRAE901_OfficeSmall_STD2019_Denver_hourly.json
energyplus_ruleset_model-0.61.dist-info/LICENSE
energyplus_ruleset_model-0.61.dist-info/METADATA
energyplus_ruleset_model-0.61.dist-info/WHEEL
energyplus_ruleset_model-0.61.dist-info/entry_points.txt
energyplus_ruleset_model-0.61.dist-info/top_level.txt
energyplus_ruleset_model-0.61.dist-info/RECORD
