Metadata-Version: 2.1
Name: energyplus_ruleset_model
Version: 0.61
Summary: A Python tool for generating RPDs.
Home-page: https://github.com/JasonGlazer/createRulesetProjectDescription
Author: Jason Glazer
License: ModifiedBSD
Keywords: energyplus
Requires-Python: >=3.7
License-File: LICENSE
Requires-Dist: jsonschema==4.17
Requires-Dist: pyyaml
